flet_fastapi/__init__.py
flet_fastapi/app.py
flet_fastapi/flet_app.py
flet_fastapi/flet_app_manager.py
flet_fastapi/flet_fastapi.py
flet_fastapi/flet_oauth.py
flet_fastapi/flet_static_files.py
flet_fastapi/flet_upload.py
flet_fastapi/oauth_state.py
flet_fastapi/once.py
flet_fastapi/version.py
flet_fastapi-0.20.2.dist-info/METADATA
flet_fastapi-0.20.2.dist-info/WHEEL
flet_fastapi-0.20.2.dist-info/RECORD
