Metadata-Version: 2.1
Name: flet-fastapi
Version: 0.20.2
Summary: Flet for Fast API - serve Flet app with Fast API server
License: Apache-2.0
Author: Appveyor Systems Inc.
Author-email: hello@flet.dev
Requires-Python: >=3.7,<4.0
Classifier: License :: OSI Approved :: Apache Software License
Classifier: Programming Language :: Python :: 3
Classifier: Programming Language :: Python :: 3.7
Classifier: Programming Language :: Python :: 3.8
Classifier: Programming Language :: Python :: 3.9
Classifier: Programming Language :: Python :: 3.10
Classifier: Programming Language :: Python :: 3.11
Classifier: Programming Language :: Python :: 3.12
Requires-Dist: fastapi (>=0.101.0,<0.102.0)
Requires-Dist: flet (==0.20.2)
Project-URL: documentation, https://flet.dev/docs
Project-URL: homepage, https://flet.dev
Project-URL: repository, https://github.com/flet-dev/flet
